django_business_metrics/__init__.py
django_business_metrics/_internal/__init__.py
django_business_metrics/_internal/metrics.py
django_business_metrics/_internal/metrics_manager.py
django_business_metrics/models.py
django_business_metrics/v0/__init__.py
django_business_metrics-1.0.0.dist-info/WHEEL
django_business_metrics-1.0.0.dist-info/METADATA
django_business_metrics-1.0.0.dist-info/RECORD
