Metadata-Version: 2.1
Name: django-business-metrics
Version: 1.0.0
Summary: Django Prometheus business metrics
License: MIT
Author: Reef Technologies
Author-email: vykintas.baltrusaitis@reef.pl
Requires-Python: >=3.9
Classifier: License :: OSI Approved :: MIT License
Classifier: Programming Language :: Python :: 3
Classifier: Programming Language :: Python :: 3.10
Classifier: Programming Language :: Python :: 3.9
Provides-Extra: dev
Requires-Dist: Django (>=3)
Requires-Dist: black (>=22.6.0); extra == "dev"
Requires-Dist: django-stubs (>=1.12.0); extra == "dev"
Requires-Dist: mypy (>=0.971); extra == "dev"
Requires-Dist: nox (>=2023); extra == "dev"
Requires-Dist: prometheus-client (>=0.13.0)
Requires-Dist: pytest (>=6); extra == "dev"
Requires-Dist: pytest-django; extra == "dev"
Requires-Dist: ruff (>=0.0.272); extra == "dev"
